LICENSE
MANIFEST.in
README.txt
ez_setup.py
heapdict.py
setup.py
test_heap.py
HeapDict.egg-info/PKG-INFO
HeapDict.egg-info/SOURCES.txt
HeapDict.egg-info/dependency_links.txt
HeapDict.egg-info/top_level.txt
HeapDict.egg-info/zip-safe