Metadata-Version: 1.1
Name: HeapDict
Version: 0.1.2
Summary: a heap with decrease-key and increase-key operations
Home-page: http://stutzbachenterprises.com/heap/
Author: Stutzbach Enterprises, LLC
Author-email: daniel@stutzbachenterprises.com
License: BSD
Keywords: heap decrease-key increase-key dictionary Dijkstra A*
Platform: UNKNOWN
Classifier: Development Status :: 4 - Beta
Classifier: Intended Audience :: Developers
Classifier: License :: OSI Approved :: BSD License
Classifier: Programming Language :: Python :: 2.6
Classifier: Programming Language :: Python :: 2.7
Classifier: Programming Language :: Python :: 3.0
Classifier: Programming Language :: Python :: 3.1
Provides: heapdict
